nervlib/__init__.py
nervlib/brainfuck.py
nervlib-0.0.1.dist-info/METADATA
nervlib-0.0.1.dist-info/WHEEL
nervlib-0.0.1.dist-info/top_level.txt
nervlib-0.0.1.dist-info/RECORD
