Metadata-Version: 2.1
Name: nervlib
Version: 0.0.1
Summary: sex
Home-page: https://github.com/kosero/nervlib
Author: kosero
Author-email: kosero@tuta.io
